tests
pymuxinator
