Metadata-Version: 1.0
Name: pymuxinator
Version: 0.0.6
Summary: Tmux session manager
Home-page: http://mingle.cm
Author: Caleb Mingle
Author-email: caleb@mingle.cm
License: UNKNOWN
Platform: UNKNOWN
